pipfonts/__init__.py
pipfonts-1.0.0.dist-info/METADATA
pipfonts-1.0.0.dist-info/WHEEL
pipfonts-1.0.0.dist-info/top_level.txt
pipfonts-1.0.0.dist-info/RECORD
