Metadata-Version: 2.1
Name: pipfonts
Version: 1.0.0
Summary: A Package to Manage Fonts in the Terminal.
Home-page: UNKNOWN
Author: ЕntchenBuilds
Author-email: ЕntchenBuilds@gmail.com
License: UNKNOWN
Keywords: python
Platform: UNKNOWN
Classifier: Operating System :: Microsoft :: Windows
